nosyupylib/__init__.py
nosyupylib/funcs.py
nosyupylib/workdone.py
nosyupylib-1.0.0.dist-info/LICENSE
nosyupylib-1.0.0.dist-info/METADATA
nosyupylib-1.0.0.dist-info/WHEEL
nosyupylib-1.0.0.dist-info/top_level.txt
nosyupylib-1.0.0.dist-info/RECORD
