Metadata-Version: 2.1
Name: nosyupylib
Version: 1.0.0
Summary: NoSyu Python Library
Home-page: https://github.com/NoSyu/nosyupylib
Author: JinYeong Bak
Author-email: dongdm@gmail.com
License: MIT
Platform: UNKNOWN
Classifier: Development Status :: 4 - Beta
Classifier: License :: OSI Approved :: MIT License
Classifier: Programming Language :: Python
Classifier: Programming Language :: Python :: 3.5
Classifier: Programming Language :: Python :: 3.6
Classifier: Topic :: Software Development :: Libraries
Classifier: Topic :: Software Development :: Libraries :: Python Modules
Classifier: Intended Audience :: Developers
Requires-Python: >=3.5
Requires-Dist: slack
Requires-Dist: pymsteams
